Landsat578-0.3.78.dist-info/DESCRIPTION.rst
Landsat578-0.3.78.dist-info/METADATA
Landsat578-0.3.78.dist-info/RECORD
Landsat578-0.3.78.dist-info/WHEEL
Landsat578-0.3.78.dist-info/entry_points.txt
Landsat578-0.3.78.dist-info/metadata.json
Landsat578-0.3.78.dist-info/top_level.txt
landsat/__init__.py
landsat/download_composer.py
landsat/landsat.py
landsat/sample_script.py
landsat/usgs_download.py
landsat/web_tools.py
