Metadata-Version: 2.0
Name: Landsat578
Version: 0.3.78
Summary: Very simple API to download Landsat data from LT5, LE7, and LC8 from USGS
Home-page: https://github.com/dgketchum
Author: David Ketchum
Author-email: dgketchum@gmail.com
License: Apache
Download-URL: https://github.com/dgketchum/Landsat578/archive/0.3.78.tar.gz
Keywords: landsat download hydrology remote sensing
Platform: Posix; MacOS X; Windows
Classifier: Development Status :: 3 - Alpha
Classifier: Intended Audience :: Science/Research
Classifier: Topic :: Scientific/Engineering :: GIS
Classifier: License :: OSI Approved :: Apache Software License
Classifier: Programming Language :: Python :: 2.7
Requires-Dist: lxml
Requires-Dist: numpy
Requires-Dist: pandas
Requires-Dist: python-dateutil
Requires-Dist: pytz
Requires-Dist: requests
Requires-Dist: six
